jpsapp/__init__.py
jpsapp/__main__.py
jpsapp/main.py
jpsapp/py.typed
jpsapp-1.1.10.dist-info/LICENSE
jpsapp-1.1.10.dist-info/METADATA
jpsapp-1.1.10.dist-info/WHEEL
jpsapp-1.1.10.dist-info/entry_points.txt
jpsapp-1.1.10.dist-info/top_level.txt
jpsapp-1.1.10.dist-info/RECORD
