Metadata-Version: 2.1
Name: jpsapp
Version: 1.1.10
Summary: An example of Python application distribution.
Author-email: JP Hutchins <jphutchins@gmail.com>
License: Apache License
Project-URL: Homepage, https://dev.to/jphutchins/building-a-universally-portable-python-app-2gng
Project-URL: Repository, https://github.com/JPhutchins/python-distribution-example.git
Classifier: Development Status :: 4 - Beta
Classifier: Intended Audience :: Developers
Classifier: Topic :: Software Development :: Build Tools
Requires-Python: >=3.8
License-File: LICENSE
Provides-Extra: dev
Requires-Dist: build <2,>=1.2.1 ; extra == 'dev'
Requires-Dist: pyinstaller <7,>=6.4.0 ; extra == 'dev'
Requires-Dist: pyinstaller-versionfile <3,>=2.1.1 ; extra == 'dev'
